trixeditor/__init__.py
trixeditor/admin.py
trixeditor/apps.py
trixeditor/fields.py
trixeditor/views.py
trixeditor/widgets.py
trixeditor/static/widgets/css/trix.css
trixeditor/static/widgets/js/trix.umd.min.js
trixeditor/templates/trixeditor/widgets/trix.html
django_trix_richtext-2.0.8.dist-info/LICENSE
django_trix_richtext-2.0.8.dist-info/WHEEL
django_trix_richtext-2.0.8.dist-info/METADATA
django_trix_richtext-2.0.8.dist-info/RECORD
