Metadata-Version: 2.1
Name: django-trix-richtext
Version: 2.0.8
Summary: trix editor for django
Keywords: django,trix,trix editor
Author-email: Weinan Tang <twn39@163.com>
Requires-Python: >=3.5
Classifier: License :: OSI Approved :: MIT License
Classifier: Framework :: Django
Classifier: Framework :: Django :: 4.2
Classifier: Framework :: Django :: 5.0
Requires-Dist: Django >=4.0
Project-URL: Home, https://github.com/twn39
